sam_cfn_publish/__init__.py
sam_cfn_publish/__main__.py
sam_cfn_publish/helpers.py
sam_cfn_publish/inline_functions.py
sam_cfn_publish/move_assets.py
sam_cfn_publish/sam_translate.py
sam_cfn_publish/tags_metadata.py
sam_cfn_publish-0.2.3.dist-info/LICENSE
sam_cfn_publish-0.2.3.dist-info/METADATA
sam_cfn_publish-0.2.3.dist-info/WHEEL
sam_cfn_publish-0.2.3.dist-info/entry_points.txt
sam_cfn_publish-0.2.3.dist-info/top_level.txt
sam_cfn_publish-0.2.3.dist-info/RECORD
