Metadata-Version: 2.1
Name: sam-cfn-publish
Version: 0.2.3
Summary: A tool for formatting AWS Serverless Application Model (SAM) templates to CloudFormation for publishing
Home-page: https://github.com/peterjdavis/sam-cfn-publish
Author: Pete Davis
Author-email: pete@peterjdavis.info
Keywords: "SAM","CloudFormation","Serverless Application Model"
Classifier: Programming Language :: Python :: 3
Requires-Python: !=4.0,<=4.0,>=3.7
License-File: LICENSE
Requires-Dist: boto3
Requires-Dist: cfn-flip
Requires-Dist: aws-sam-translator
Provides-Extra: pdf
Requires-Dist: ReportLab >=1.2 ; extra == 'pdf'
Requires-Dist: RXP ; extra == 'pdf'
Provides-Extra: rest
Requires-Dist: docutils >=0.3 ; extra == 'rest'
Requires-Dist: pack ==1.1,==1.3 ; extra == 'rest'
